{
    "Filename": "Shows",
    "Description List": [
        "superboiz",
        "Invincible",
        "Last Week Tonight"
    ],
    "Data": [
        {
            "Description": "superboiz",
            "Incognito": "No",
            "Links": [
                "https://play.hbomax.com/show/759711ff-f46f-4c29-9134-84e247e0e7da"
            ]
        },
        {
            "Description": "Invincible",
            "Incognito": "No",
            "Links": [
                "https://meoo.ro/invincible-2021-subtitrat-68/vizioneaza/s\\{Season\\}/e\\{Episode\\}/"
            ]
        },
        {
            "Description": "Last Week Tonight",
            "Incognito": "No",
            "Links": [
                "https://play.hbomax.com/topical/f7ebcd02-6641-4ec5-a392-07e58196808f"
            ]
        }
    ]
}